AutoKS/__init__.py
AutoKS/calc_gcent.py
AutoKS/calc_graphical_matching.py
AutoKS/calc_surface_matching.py
AutoKS/calc_tversky.py
AutoKS/cmap2graph.py
AutoKS/draw.py
AutoKS/get_data_files_name.py
AutoKS/graph2prxfile.py
AutoKS/numerical_sim.py
AutoKS/pathfinder_network.py
AutoKS/read_file.py
AutoKS/text2graph.py
AutoKS-0.0.28.dist-info/LICENSE
AutoKS-0.0.28.dist-info/METADATA
AutoKS-0.0.28.dist-info/WHEEL
AutoKS-0.0.28.dist-info/top_level.txt
AutoKS-0.0.28.dist-info/RECORD
