Metadata-Version: 2.1
Name: AutoKS
Version: 0.0.28
Summary: An easy-to-used Python package to process knowledge structure data automatically
Home-page: https://github.com/weiziqian1996/AutoKS
Author: Wei Zi-Qian
Author-email: weiziqian1996@163.com
Requires-Python: >=3.6
License-File: LICENSE
Requires-Dist: numpy
Requires-Dist: pywebview
Requires-Dist: networkx
